{
  "id": "einstein",
  "name": "アルベルト・アインシュタイン",
  "nameEn": "Albert Einstein",
  "birth": 1879,
  "death": 1955,
  "country": "ドイツ → スイス → アメリカ",
  "field": "理論物理学者",
  "summary": "特許局の技師から相対性理論を打ち立てた20世紀最大の科学者。ナチスを逃れアメリカへ亡命、原爆開発を進言しながら後半生は平和運動に捧げた。",
  "events": [
    {
      "year": 1879,
      "age": 0,
      "title": "ドイツ・ウルムに誕生",
      "detail": "言葉を話すのが遅く、教師からは『何も成し遂げないだろう』と評された。",
      "tags": []
    },
    {
      "year": 1895,
      "age": 16,
      "title": "ギムナジウムを中退、ミュンヘンを離れる",
      "detail": "軍隊式教育に馴染めず退学。父の事業失敗で一家がイタリアへ。以後、国籍を一度も持たない『無国籍』の時期を経る。",
      "tags": [
        "pride_broken",
        "restart",
        "loss"
      ]
    },
    {
      "year": 1902,
      "age": 23,
      "title": "スイス特許庁の三級審査官に",
      "detail": "大学の職に就けず、友人の父のコネで就職。この『偉大なる暇つぶし』の時間が奇跡の年を生む。",
      "tags": [
        "restart",
        "isolation"
      ]
    },
    {
      "year": 1905,
      "age": 26,
      "title": "奇跡の年、特許局で書いた4本の論文",
      "detail": "特殊相対性理論、光電効果、ブラウン運動、質量エネルギー等価性。物理学を書き換える。",
      "tags": [
        "breakthrough"
      ]
    },
    {
      "year": 1915,
      "age": 36,
      "title": "一般相対性理論完成",
      "detail": "8年かけて重力の新しい理論を構築。時空は曲がる、と。",
      "tags": [
        "breakthrough",
        "hope",
        "creation"
      ]
    },
    {
      "year": 1919,
      "age": 40,
      "title": "日食観測で一般相対論が証明され世界的スターに",
      "detail": "エディントンの遠征で星の光の曲がりが確認。翌日から『ニュートンを超えた男』として世界中の新聞1面に。",
      "tags": [
        "approval",
        "breakthrough"
      ]
    },
    {
      "year": 1921,
      "age": 42,
      "title": "ノーベル物理学賞（光電効果による）",
      "detail": "相対論ではなく光量子仮説で受賞。賞金はすべて最初の妻ミレヴァに送った。",
      "tags": [
        "approval"
      ]
    },
    {
      "year": 1933,
      "age": 54,
      "title": "ナチスを逃れアメリカへ亡命",
      "detail": "ユダヤ人迫害から逃れプリンストンへ。二度とドイツに戻らなかった。",
      "tags": [
        "escape",
        "loss"
      ]
    },
    {
      "year": 1933,
      "age": 54,
      "title": "ナチスから逃れ米国プリンストンへ",
      "detail": "ドイツに二度と戻らなかった。『私の祖国は人類だ』と語る。",
      "tags": [
        "restart",
        "isolation"
      ]
    },
    {
      "year": 1939,
      "age": 60,
      "title": "ルーズベルト大統領に原爆開発を進言",
      "detail": "ナチスの先を越すため署名。のちに『人生最大の過ち』と悔いた。",
      "tags": [
        "self_denial"
      ]
    },
    {
      "year": 1955,
      "age": 76,
      "title": "プリンストンで死去",
      "detail": "大動脈瘤破裂。墓は作らず、遺灰は秘密の場所に撒かれた。脳は研究用に保存された。",
      "tags": [
        "loss"
      ]
    }
  ],
  "quotes": [
    {
      "text": "人生には二通りの生き方しかない。奇跡など全く起こらないかのように生きるか、すべてが奇跡であるかのように生きるか。",
      "source": "書簡"
    },
    {
      "text": "想像力は知識よりも重要である。",
      "source": "インタビュー"
    },
    {
      "text": "想像力は知識よりも重要である。知識には限界があるが、想像力は世界を包みこむ。",
      "source": "『サタデー・イブニング・ポスト』1929"
    },
    {
      "text": "神はサイコロを振らない。",
      "source": "マックス・ボルンへの手紙 1926"
    },
    {
      "text": "人生には二つの生き方しかない。奇跡などないかのように生きるか、すべてが奇跡であるかのように生きるか。",
      "source": "アインシュタインに帰される言葉"
    },
    {
      "text": "同じことを繰り返しながら違う結果を望むこと、それを狂気と呼ぶ。",
      "source": "アインシュタインに帰される言葉"
    },
    {
      "text": "学校で学んだことをすべて忘れたとき、残るものが教育である。",
      "source": "1936年の講演"
    },
    {
      "text": "私には特別な才能はありません。ただ情熱的に好奇心が旺盛なだけです。",
      "source": "カール・ゼーリヒへの手紙 1952"
    },
    {
      "text": "宇宙について最も理解しがたいことは、それが理解可能であることだ。",
      "source": "『物理と実在』1936"
    },
    {
      "text": "重要なのは質問を止めないことだ。",
      "source": "ライフ誌インタビュー 1955"
    }
  ],
  "places": [
    {
      "name": "アインシュタインの家",
      "location": "ベルン（スイス）",
      "note": "特許局勤務時代の住居。『奇跡の年』の舞台",
      "image": "https://upload.wikimedia.org/wikipedia/commons/thumb/2/28/Albert_Einstein_Head_cleaned.jpg/330px-Albert_Einstein_Head_cleaned.jpg"
    },
    {
      "name": "プリンストン高等研究所",
      "location": "アメリカ・ニュージャージー州",
      "note": "晩年の研究の地",
      "image": "https://upload.wikimedia.org/wikipedia/commons/thumb/2/28/Fuld_Hall%2C_Institute_for_Advanced_Study%2C_Princeton%2C_NJ.jpg/330px-Fuld_Hall%2C_Institute_for_Advanced_Study%2C_Princeton%2C_NJ.jpg"
    },
    {
      "name": "アインシュタイン博物館",
      "location": "ベルン歴史博物館内",
      "note": "手稿や書簡を展示",
      "image": "https://upload.wikimedia.org/wikipedia/commons/thumb/0/0b/140927_Nara_National_Museum_Nara_Japan03bs5.jpg/330px-140927_Nara_National_Museum_Nara_Japan03bs5.jpg"
    }
  ],
  "imageUrl": "https://commons.wikimedia.org/wiki/Special:FilePath/Albert_Einstein_Head_cleaned.jpg?width=500",
  "wikiTitle": "アルベルト・アインシュタイン",
  "imageCredit": {
    "artist": "Orren Jack Turner",
    "license": "Public domain",
    "licenseUrl": "",
    "credit": "This image is available from the United States Library of Congress 's Prints and Photographs division under the digital ID cph.3b46036 . This tag does not indicate the copyright status of the attached work. A normal copyright tag is still required. See Commons:Licensing .",
    "sourceUrl": "https://commons.wikimedia.org/wiki/File:Albert_Einstein_Head_cleaned.jpg"
  },
  "books": [
    {
      "title": "相対性理論",
      "author": "アルベルト・アインシュタイン",
      "asin": "4003394119",
      "description": "本人による一般向け解説書"
    },
    {
      "title": "アインシュタイン わが相対性理論",
      "author": "アインシュタイン",
      "asin": "4480093281",
      "description": "思想と人生を語った自伝的エッセイ"
    },
    {
      "title": "アインシュタイン選集",
      "author": "アインシュタイン",
      "description": "本人による相対論の解説、エッセイ、書簡を集成。"
    },
    {
      "title": "アインシュタイン その生涯と宇宙",
      "author": "ウォルター・アイザックソン",
      "description": "Appleジョブズの伝記作家による決定版評伝。"
    },
    {
      "title": "アインシュタイン 150の言葉",
      "author": "ジェリー・メイヤー",
      "asin": "4887590164",
      "description": "人生を照らす天才の言葉集。"
    }
  ],
  "media": [
    {
      "title": "ジーニアス：アインシュタイン",
      "year": 2017,
      "type": "drama",
      "country": "アメリカ",
      "cast": "ジェフリー・ラッシュ／ジョニー・フリン",
      "description": "ナショジオ製作。青年期から晩年まで全10話で描く伝記ドラマ。"
    },
    {
      "title": "IQ たったひとりの恋人",
      "year": 1994,
      "type": "movie",
      "country": "アメリカ",
      "director": "フレッド・スケピシ",
      "cast": "メグ・ライアン／ウォルター・マッソー",
      "description": "アインシュタインの姪と自動車整備工のロマンチック・コメディ。"
    }
  ],
  "coverImage": "https://upload.wikimedia.org/wikipedia/commons/thumb/2/28/Albert_Einstein_Head_cleaned.jpg/330px-Albert_Einstein_Head_cleaned.jpg",
  "coverImageCaption": "アインシュタインの家",
  "happenings": [
    {
      "type": "exhibition",
      "title": "アインシュタイン・ハウス",
      "venue": "スイス・ベルン",
      "period": "通年",
      "url": "https://www.einstein-bern.ch/",
      "description": "特許庁時代に住み『奇跡の年』の論文を書いたアパート。"
    },
    {
      "type": "goods",
      "title": "アインシュタイン肖像グッズ",
      "venue": "ミュージアムショップ・通販",
      "url": "https://www.amazon.co.jp/s?k=%E3%82%A2%E3%82%A4%E3%83%B3%E3%82%B7%E3%83%A5%E3%82%BF%E3%82%A4%E3%83%B3+%E3%82%B0%E3%83%83%E3%82%BA",
      "description": "あの有名な舌を出した写真のTシャツ・マグカップ・ポスターなど。"
    }
  ],
  "works": [
    {
      "title": "相対性理論 解説",
      "year": 1905,
      "type": "理論",
      "description": "特殊相対論と一般相対論をやさしく。",
      "youtubeSearchUrl": "https://www.youtube.com/results?search_query=%E3%82%A2%E3%83%AB%E3%83%99%E3%83%AB%E3%83%88%E3%83%BB%E3%82%A2%E3%82%A4%E3%83%B3%E3%82%B7%E3%83%A5%E3%82%BF%E3%82%A4%E3%83%B3%20%E7%9B%B8%E5%AF%BE%E6%80%A7%E7%90%86%E8%AB%96%20%E8%A7%A3%E8%AA%AC"
    },
    {
      "title": "E=mc² の意味",
      "year": 1905,
      "type": "理論",
      "description": "質量とエネルギーの等価性。",
      "youtubeSearchUrl": "https://www.youtube.com/results?search_query=%E3%82%A2%E3%83%AB%E3%83%99%E3%83%AB%E3%83%88%E3%83%BB%E3%82%A2%E3%82%A4%E3%83%B3%E3%82%B7%E3%83%A5%E3%82%BF%E3%82%A4%E3%83%B3%20E%3Dmc%C2%B2%20%E3%81%AE%E6%84%8F%E5%91%B3"
    }
  ],
  "birthMonth": 3,
  "birthDay": 14,
  "deathMonth": 4,
  "deathDay": 18,
  "routine": [
    {
      "start": 0,
      "end": 9,
      "activity": "睡眠（最低10時間）",
      "cat": "sleep"
    },
    {
      "start": 9,
      "end": 10,
      "activity": "朝食・コーヒーを淹れる",
      "cat": "meal"
    },
    {
      "start": 10,
      "end": 13,
      "activity": "プリンストン高等研究所で思考",
      "cat": "work"
    },
    {
      "start": 13,
      "end": 14,
      "activity": "昼食（家で）",
      "cat": "meal"
    },
    {
      "start": 14,
      "end": 15,
      "activity": "昼寝（欠かさない）",
      "cat": "sleep"
    },
    {
      "start": 15,
      "end": 19,
      "activity": "研究・訪問者との議論",
      "cat": "work"
    },
    {
      "start": 19,
      "end": 20,
      "activity": "夕食・ヴァイオリン演奏",
      "cat": "leisure"
    },
    {
      "start": 20,
      "end": 22,
      "activity": "手紙執筆・書斎",
      "cat": "work"
    },
    {
      "start": 22,
      "end": 24,
      "activity": "読書・就寝準備",
      "cat": "leisure"
    }
  ],
  "lifeDigest": "ドイツ生まれの理論物理学者。特殊相対性理論、一般相対性理論、相対論的宇宙論、ブラウン運動に関する揺動散逸定理、光量子仮説、アインシュタイン模型、零点エネルギーの導入、半古典型のシュレディンガー方程式、ボース＝アインシュタイン凝縮等多数の業績で知られる。それまでの物理学の認識を根本から変え、「20世紀最大の物理学者」とも評される。",
  "traits": {
    "foods": [
      "スパゲッティ（シンプルなトマトソース）",
      "卵",
      "果物",
      "タバコ（パイプ）"
    ],
    "hobbies": [
      "ヴァイオリン演奏（モーツァルトとバッハ）",
      "セーリング",
      "読書（哲学）"
    ],
    "personality": "穏やかで子供のような好奇心。権威を嫌い、思考実験を楽しんだ。『想像力は知識より重要』と信じ、常に純粋な驚きを失わなかった。",
    "likes": [
      "モーツァルト",
      "スピノザの哲学",
      "帆船"
    ],
    "dislikes": [
      "靴下（履かない）",
      "形式張った儀式",
      "権威主義"
    ]
  },
  "relations": [
    {
      "name": "ニールス・ボーア",
      "relation": "生涯の論敵",
      "note": "量子力学の解釈を巡る論争。『神はサイコロを振らない』。"
    },
    {
      "name": "マックス・プランク",
      "relation": "支援者・同志"
    },
    {
      "name": "シュレーディンガー",
      "relation": "同盟者"
    },
    {
      "name": "ミケーレ・ベッソ",
      "relation": "生涯の親友"
    },
    {
      "name": "ミレヴァ・マリッチ",
      "relation": "最初の妻"
    },
    {
      "name": "エルザ・アインシュタイン",
      "relation": "二度目の妻"
    },
    {
      "id": "bertrand_russell",
      "name": "バートランド・ラッセル",
      "relation": "反核の同志"
    },
    {
      "name": "ハイゼンベルク",
      "relation": "不確定性への批判"
    },
    {
      "name": "ナチス政権",
      "relation": "追われた体制",
      "note": "1933年ドイツを離れプリンストンへ。"
    }
  ],
  "innerConflicts": [
    {
      "title": "最初の妻ミレヴァとの関係と、見捨てた娘リーゼル",
      "period": "1902〜1919",
      "body": "物理学を志す同級生ミレヴァ・マリッチと恋愛、結婚前に娘リーゼルを出産（1902）。しかしリーゼルは『私生児』として記録から消され、養子に出されるか早逝したとされる。アインシュタインは彼女に一度も会わなかった可能性が高い。1914年以降、ミレヴァとの関係は冷え、『話しかけるな、食事を一緒にするな』という契約書まで突きつけた。ノーベル賞金はすべてミレヴァに渡すことで離婚を成立させた。『私は最も愛する人を、最も傷つけた』と晩年の手紙で告白。"
    },
    {
      "title": "原爆の父という烙印と、その後の贖罪",
      "period": "1939〜1955",
      "body": "1939年ルーズベルト大統領へ原爆開発の可能性を伝える書簡に署名（レオ・シラードの草稿に署名したのみだが影響は大きかった）。結果マンハッタン計画が始まり、広島・長崎へ投下。『もし原爆が作られることを知っていたら、私は靴屋になっていた』と1954年の対談で発言。その後パグウォッシュ会議の発起人となり核廃絶運動の顔となったが、罪悪感は最期まで消えなかった。"
    },
    {
      "title": "量子力学を受け入れられなかった老いた革命家",
      "period": "1925〜1955",
      "body": "自身が打ち立てた理論が量子力学を生んだのに、その『確率的』な世界観を生涯認めなかった。『神はサイコロを振らない』と繰り返し、ボーアとの論争は30年続いた。EPRパラドックスで量子力学の不完全性を指摘したが、後の実験（ベルの不等式）は逆に量子力学を支持。革命家がいつか保守派になる、という科学史のパラドックスを体現した。"
    }
  ],
  "turningPoints": [
    {
      "year": 1905,
      "title": "奇跡の年（Annus Mirabilis）— 26歳、特許庁の事務員が世界を変えた",
      "body": "スイス特許庁の審査官として働きながら、1年間で4つの歴史的論文を発表。光量子仮説（後のノーベル賞）、ブラウン運動、特殊相対性理論、E=mc²。教授職にも就いていない無名の26歳が、近代物理学を再構築した。『自分で時間を作るしかなかった。特許の仕事が終わった夜、計算した』。"
    },
    {
      "year": 1915,
      "title": "一般相対性理論の完成 — 10年の計算との格闘",
      "body": "特殊相対性理論（1905）を重力にも拡張しようと10年をかけた計算の末、1915年ベルリンで完成。『数学者に助けを求めた日もあった。独りでは無理だった』と後に告白。1919年の日食観測で光が太陽の重力で曲がることが確認され、世界的センセーションに。新聞の一面を埋め尽くす『科学のニュートン』の後継者として、研究者から神話的人物へ変貌した。"
    },
    {
      "year": 1933,
      "title": "ナチスからの逃亡 — ドイツ市民権を捨てプリンストンへ",
      "body": "アメリカ滞在中にナチスが政権を取り、ドイツに戻らない決断。自宅と財産は没収、『ユダヤ人物理学』として相対性理論は禁書に。プリンストン高等研究所の職を受け、以後22年間アメリカで過ごした。市民権を2度捨てた男（ドイツ→スイス→アメリカ）。『祖国』より『人類』を選んだ生き方は晩年まで貫かれる。"
    }
  ],
  "unknownStories": [
    {
      "title": "靴下を履かない偉大なる物理学者",
      "body": "『親指が必ず靴下を突き破る。だから履かないことにした』と論理的に説明した。プリンストンの冬でもサンダルで歩き、大統領就任の晩餐会にも靴下なしで出席。形式主義への抵抗というより、合理主義の徹底。"
    },
    {
      "title": "FBIファイル1427ページの監視対象だった",
      "body": "アメリカに移住後、原爆反対・公民権支持・社会主義的発言などでFBI長官J・エドガー・フーヴァーに目をつけられ、22年間で1427ページの監視ファイルが作成された。電話盗聴、ゴミ漁り、秘書への尋問。『自由の国』が生涯科学者を疑い続けた皮肉な記録。"
    },
    {
      "title": "イスラエル大統領就任を断った",
      "body": "1952年、初代イスラエル大統領ハイム・ヴァイツマンの死去に伴い、第2代大統領として就任を要請された。『人類を扱うには、私はあまりに世間知らずだ。数式なら扱えるが、人間は扱えない』と辞退。ユダヤ人のアイデンティティは強く持ちながら、政治から距離を置いた。"
    }
  ]
}