{
  "id": "elvis",
  "name": "エルヴィス・プレスリー",
  "nameEn": "Elvis Presley",
  "birth": 1935,
  "death": 1977,
  "country": "アメリカ",
  "field": "歌手",
  "summary": "ロックンロールの王様（King of Rock and Roll）。白人と黒人音楽を融合させ、20世紀ポップカルチャーの偶像となった。",
  "wikiTitle": "エルヴィス・プレスリー",
  "events": [],
  "quotes": [],
  "places": [],
  "imageUrl": "assets/portraits/elvis.webp",
  "books": [],
  "media": [],
  "works": [],
  "routine": {},
  "lifeDigest": "",
  "traits": {},
  "relations": [],
  "imageUrlSource": "https://commons.wikimedia.org/wiki/Special:FilePath/Elvis_Presley_promoting_Jailhouse_Rock.jpg?width=500"
}
