{
  "id": "freud",
  "name": "ジークムント・フロイト",
  "nameEn": "Sigmund Freud",
  "birth": 1856,
  "death": 1939,
  "country": "オーストリア → イギリス",
  "field": "精神分析学者・医師",
  "summary": "『無意識』『性欲』『エディプスコンプレックス』で20世紀を書き換えた精神分析の創始者。ナチスを逃れロンドンへ亡命、口腔癌で死去。",
  "events": [
    {
      "year": 1856,
      "age": 0,
      "title": "モラヴィアのユダヤ人商家に誕生",
      "detail": "毛織物商の父。4歳でウィーンに移住。",
      "tags": []
    },
    {
      "year": 1885,
      "age": 29,
      "title": "パリでシャルコーに学ぶ",
      "detail": "催眠によるヒステリー治療を学ぶ。精神分析の原点。",
      "tags": [
        "turning_encounter"
      ]
    },
    {
      "year": 1886,
      "age": 30,
      "title": "マルタ・ベルナイスと結婚、4年の婚約期間を経て",
      "detail": "財政難で4年待たされた婚約。6人の子をもうけ、特に末子アンナが精神分析を継ぐ。",
      "tags": [
        "turning_encounter"
      ]
    },
    {
      "year": 1895,
      "age": 39,
      "title": "親友ブロイアーと共著『ヒステリー研究』",
      "detail": "アンナ・O の症例から精神分析誕生。しかし師弟関係はこの数年で破綻する。",
      "tags": [
        "breakthrough"
      ]
    },
    {
      "year": 1896,
      "age": 40,
      "title": "父ヤーコプの死",
      "detail": "『父の死は、人生で最も重要な出来事だ』と書く。自己分析と『夢判断』の出発点。",
      "tags": [
        "loss"
      ]
    },
    {
      "year": 1900,
      "age": 44,
      "title": "『夢判断』出版",
      "detail": "無意識の発見。発売直後は売れず、6年で600部しか売れなかった。",
      "tags": [
        "breakthrough",
        "setback"
      ]
    },
    {
      "year": 1909,
      "age": 53,
      "title": "ユングと共にクラーク大学訪問、米国で講演",
      "detail": "初の国際的認知。アメリカで精神分析が広まるきっかけ。",
      "tags": [
        "approval",
        "breakthrough"
      ]
    },
    {
      "year": 1910,
      "age": 54,
      "title": "ユングを後継者に指名、のち決別",
      "detail": "『息子』と呼んだユングが1913年に無意識論の相違で離反。最も深い傷となった。",
      "tags": [
        "heartbreak",
        "pride_broken"
      ]
    },
    {
      "year": 1914,
      "age": 58,
      "title": "ユングと決別、『ナルシシズム入門』で反論",
      "detail": "5年続いた親子のような関係の終わり。『王子の裏切り』として記憶される。",
      "tags": [
        "loss",
        "pride_broken"
      ]
    },
    {
      "year": 1923,
      "age": 67,
      "title": "口腔癌の診断、以後16年闘病",
      "detail": "33回の手術、義歯、痛みに耐えながら著作を続けた。",
      "tags": [
        "illness"
      ]
    },
    {
      "year": 1923,
      "age": 67,
      "title": "口蓋癌の手術、以後33回の手術",
      "detail": "葉巻を愛し続けた代償。それでも書き続けた。",
      "tags": [
        "illness"
      ]
    },
    {
      "year": 1938,
      "age": 82,
      "title": "ナチスを逃れロンドンへ亡命",
      "detail": "著書は焚書に。『私の著書が焼かれるのは時代の進歩だ』と皮肉った。",
      "tags": [
        "escape",
        "loss"
      ]
    },
    {
      "year": 1939,
      "age": 83,
      "title": "ロンドンで安楽死",
      "detail": "癌の激痛に耐えきれず、主治医に致死量のモルヒネを要請。",
      "tags": [
        "loss",
        "illness"
      ]
    }
  ],
  "quotes": [
    {
      "text": "無意識は意識より広大な心の部分である。",
      "source": "『夢判断』"
    },
    {
      "text": "愛することと働くこと。これがすべてである。",
      "source": "インタビュー"
    },
    {
      "text": "どこにエスがあったか、そこに自我があるべきだ。",
      "source": "『続精神分析入門講義』"
    },
    {
      "text": "愛することと働くこと。これが健康のしるしだ。",
      "source": "フロイトに帰される言葉"
    },
    {
      "text": "無意識は意識の上に立ち、意識は無意識に働きかける。",
      "source": "『精神分析入門』"
    },
    {
      "text": "夢は無意識への王道である。",
      "source": "『夢判断』"
    },
    {
      "text": "私たちが自分について知っていることは、私たちを実際に動かしているものに比べれば微々たるものだ。",
      "source": "『精神分析入門』"
    }
  ],
  "relations": [
    {
      "name": "カール・グスタフ・ユング",
      "relation": "愛弟子 → 決別した相手",
      "years": "1907–1913",
      "note": "後継者と期待された愛弟子。性欲論の解釈をめぐり決別"
    },
    {
      "name": "マルタ・ベルナイス",
      "relation": "妻",
      "years": "1886–1939",
      "note": "53年連れ添った妻。6人の子をもうけた"
    },
    {
      "name": "アンナ・フロイト",
      "relation": "娘 / 後継者",
      "years": "生涯",
      "note": "末娘。父の精神分析を継承し児童精神分析を確立"
    }
  ],
  "places": [
    {
      "name": "ジークムント・フロイト博物館",
      "location": "オーストリア・ウィーン",
      "note": "ベルクガッセ19番地の診療所兼自宅",
      "image": "https://upload.wikimedia.org/wikipedia/commons/thumb/3/30/Berggasse_Vienna_March_2007_002.jpg/330px-Berggasse_Vienna_March_2007_002.jpg"
    },
    {
      "name": "フロイト博物館ロンドン",
      "location": "イギリス・ロンドン",
      "note": "亡命先の最後の家",
      "image": "https://upload.wikimedia.org/wikipedia/commons/thumb/3/36/Sigmund_Freud%2C_by_Max_Halberstadt_%28cropped%29.jpg/330px-Sigmund_Freud%2C_by_Max_Halberstadt_%28cropped%29.jpg"
    },
    {
      "name": "中央墓地",
      "location": "ウィーン",
      "note": "遺灰はロンドンのゴルダース・グリーン",
      "image": "https://upload.wikimedia.org/wikipedia/commons/thumb/8/82/Simmering_%28Wien%29_-_Luegerkirche_%281%29.JPG/330px-Simmering_%28Wien%29_-_Luegerkirche_%281%29.JPG"
    }
  ],
  "books": [
    {
      "title": "夢判断 上",
      "author": "ジークムント・フロイト",
      "asin": "4102038019",
      "description": "無意識を発見した20世紀最大の書"
    },
    {
      "title": "精神分析入門 上",
      "author": "フロイト",
      "asin": "4102038035",
      "description": "精神分析の世界観を自ら解説した入門書"
    }
  ],
  "imageUrl": "https://upload.wikimedia.org/wikipedia/commons/thumb/3/36/Sigmund_Freud%2C_by_Max_Halberstadt_%28cropped%29.jpg/500px-Sigmund_Freud%2C_by_Max_Halberstadt_%28cropped%29.jpg",
  "wikiTitle": "ジークムント・フロイト",
  "imageCredit": {
    "artist": "Max Halberstadt",
    "license": "Public domain",
    "licenseUrl": "",
    "credit": "https://www.christies.com/lotfinder/lot_details.aspx?intObjectID=6116407",
    "sourceUrl": "https://commons.wikimedia.org/wiki/File:Sigmund_Freud%2C_by_Max_Halberstadt_%28cropped%29.jpg"
  },
  "media": [
    {
      "title": "危険なメソッド",
      "year": 2011,
      "type": "movie",
      "country": "英・独・カナダ",
      "director": "デヴィッド・クローネンバーグ",
      "cast": "ヴィゴ・モーテンセン／マイケル・ファスベンダー",
      "description": "フロイト・ユング・ザビーナの三角関係を描く。精神分析誕生の瞬間。"
    }
  ],
  "coverImage": "https://upload.wikimedia.org/wikipedia/commons/thumb/3/30/Berggasse_Vienna_March_2007_002.jpg/330px-Berggasse_Vienna_March_2007_002.jpg",
  "coverImageCaption": "ジークムント・フロイト博物館",
  "works": [
    {
      "title": "精神分析とは",
      "year": 1900,
      "type": "理論",
      "description": "無意識・エス・自我・超自我。",
      "youtubeSearchUrl": "https://www.youtube.com/results?search_query=%E3%82%B8%E3%83%BC%E3%82%AF%E3%83%A0%E3%83%B3%E3%83%88%E3%83%BB%E3%83%95%E3%83%AD%E3%82%A4%E3%83%88%20%E7%B2%BE%E7%A5%9E%E5%88%86%E6%9E%90%E3%81%A8%E3%81%AF"
    },
    {
      "title": "夢判断 解説",
      "year": 1900,
      "type": "著作",
      "description": "『夢は無意識への王道である』。",
      "youtubeSearchUrl": "https://www.youtube.com/results?search_query=%E3%82%B8%E3%83%BC%E3%82%AF%E3%83%A0%E3%83%B3%E3%83%88%E3%83%BB%E3%83%95%E3%83%AD%E3%82%A4%E3%83%88%20%E5%A4%A2%E5%88%A4%E6%96%AD%20%E8%A7%A3%E8%AA%AC"
    }
  ],
  "birthMonth": 5,
  "birthDay": 6,
  "deathMonth": 9,
  "deathDay": 23,
  "routine": [
    {
      "start": 0,
      "end": 7,
      "activity": "睡眠",
      "cat": "sleep"
    },
    {
      "start": 7,
      "end": 8,
      "activity": "起床・ひげを整える（毎日床屋を呼んだ）",
      "cat": "exercise"
    },
    {
      "start": 8,
      "end": 9,
      "activity": "朝食・ウィーンの新聞",
      "cat": "meal"
    },
    {
      "start": 9,
      "end": 13,
      "activity": "患者の診察（8人、各45分）",
      "cat": "work"
    },
    {
      "start": 13,
      "end": 14,
      "activity": "昼食（正確に1時間）",
      "cat": "meal"
    },
    {
      "start": 14,
      "end": 15,
      "activity": "市街散歩・葉巻",
      "cat": "exercise"
    },
    {
      "start": 15,
      "end": 21,
      "activity": "診察（さらに6時間）",
      "cat": "work"
    },
    {
      "start": 21,
      "end": 22,
      "activity": "家族と夕食",
      "cat": "meal"
    },
    {
      "start": 22,
      "end": 24,
      "activity": "執筆・手紙・さらに葉巻（1日20本）",
      "cat": "work"
    }
  ]
}