{
  "id": "maria_callas",
  "name": "マリア・カラス",
  "nameEn": "Maria Callas",
  "birth": 1923,
  "death": 1977,
  "country": "ギリシャ／アメリカ",
  "field": "ソプラノ歌手（オペラの女王）",
  "summary": "20世紀最大のソプラノ、オペラの女王『ラ・ディヴィーナ（神聖なる女性）』。劇的表現力と超絶技巧でベルカント・オペラを蘇らせ、歌だけでなく演技でオペラを総合芸術に引き上げた伝説の歌姫。",
  "events": [
    { "year": 1923, "age": 0, "title": "ニューヨークにギリシャ系移民の子として生まれる", "detail": "本名マリア・アンナ・ソフィア・セシリア・カロゲロプーロス。幼少期から母に歌を叩き込まれた。" },
    { "year": 1937, "age": 14, "title": "家族と共にギリシャへ帰国", "detail": "アテネ音楽院で名教師エルヴィラ・デ・ヒダルゴに師事。ベルカント唱法を学ぶ。" },
    { "year": 1942, "age": 18, "title": "プロ・デビュー（アテネ）", "detail": "プッチーニ『トスカ』でデビュー。第二次大戦下の混乱の中で。", "tags": ["breakthrough"] },
    { "year": 1947, "age": 24, "title": "イタリア・デビュー（ヴェローナ）", "detail": "ポンキエッリ『ラ・ジョコンダ』で大成功、夫となるメネギーニと出会う。" },
    { "year": 1949, "age": 26, "title": "同じ週にベルカント２作品主演という奇跡", "detail": "ヴェネツィアで同じ週にワーグナー重量級とベッリーニ軽量ベルカントを歌い分け、歴史的事件に。", "tags": ["breakthrough"] },
    { "year": 1954, "age": 31, "title": "ミラノ・スカラ座の女王", "detail": "カラスのための劇場と呼ばれるほどスカラ座に君臨。ヴィスコンティ演出『椿姫』が伝説に。", "tags": ["approval"] },
    { "year": 1957, "age": 34, "title": "スカラ座『アンナ・ボレーナ』", "detail": "忘れられていたドニゼッティのオペラを蘇らせ、ベルカント・リバイバルの旗手に。" },
    { "year": 1959, "age": 36, "title": "オナシスと運命の出会い", "detail": "ギリシャの海運王アリストテレス・オナシスと恋愛、夫メネギーニと別れる。キャリアの頂点と私生活の激震。" },
    { "year": 1968, "age": 45, "title": "オナシス、ジャクリーン・ケネディと結婚", "detail": "カラスは深く傷つき、舞台を離れる。" },
    { "year": 1974, "age": 51, "title": "最後の世界ツアー", "detail": "声は衰えていたが『声は失っても、音楽への愛は失わない』と続けた。" },
    { "year": 1977, "age": 53, "title": "パリのアパルトマンで死去", "detail": "心臓発作。孤独のうちに53歳で逝去。遺灰はエーゲ海に撒かれた。" }
  ],
  "quotes": [
    { "text": "私はオペラではなく、人間を歌うの。", "source": "インタビュー" },
    { "text": "芸術家は幸せになる権利がない。私たちは自分の魂を与えるのだから。", "source": "対談" },
    { "text": "声を失っても、音楽への愛は失わない。", "source": "晩年の言葉" }
  ],
  "relations": [
    { "name": "ルチアーノ・パヴァロッティ", "id": "", "relation": "次世代の後輩", "note": "カラスに敬意を表し続けた" }
  ],
  "places": [
    { "name": "ミラノ・スカラ座", "location": "イタリア・ミラノ", "note": "カラスの聖地" },
    { "name": "パリ・アパルトマン", "location": "フランス・パリ16区Avenue Georges Mandel 36", "note": "晩年を過ごし、逝去した場所" }
  ],
  "books": [
    { "title": "カラス自伝", "author": "マリア・カラス", "description": "死の年に遺された自伝" },
    { "title": "マリア・カラス伝", "author": "アルド・エル・ファルラ", "description": "伝説の歌姫の決定版伝記" }
  ],
  "imageUrl": "https://upload.wikimedia.org/wikipedia/commons/thumb/5/5f/Callasnewyork.jpg/280px-Callasnewyork.jpg",
  "wikiTitle": "マリア・カラス",
  "birthMonth": 12,
  "birthDay": 2,
  "lifeDigest": "20世紀最大のソプラノ、オペラの女王と呼ばれたギリシャ系アメリカ人歌手。ベルカント唱法を極め、ワーグナー重量級からベッリーニ軽量ベルカントまで歌い分ける驚異の技巧と、役になりきる劇的表現力で『歌うだけのオペラ』を『演じるオペラ』に変えた。ミラノ・スカラ座の女王として1950年代に頂点。海運王オナシスとの恋愛でメディアに晒され、オナシスがジャッキー・ケネディと結婚した衝撃で舞台を離れた。晩年は声の衰えと孤独の中、1977年パリのアパルトマンで53歳で逝去。『ラ・ディヴィーナ（神聖なる女性）』の名は今も生きる。",
  "traits": {
    "foods": ["イタリア料理（トスカーナ風）", "エスプレッソ", "ギリシャ料理", "ワイン（赤のバローロ）"],
    "hobbies": ["読書（プルースト、シェイクスピア）", "犬（プードル飼育）", "高級ファッション", "映画鑑賞"],
    "personality": "完璧主義、繊細、情熱的。舞台では女王だが私生活では傷つきやすく孤独を抱えた。",
    "likes": ["スカラ座の舞台", "最高級のベルカント", "静寂のパリ"],
    "dislikes": ["声の衰えを指摘されること", "裏切り", "平凡な演奏"]
  }
}
