{
  "id": "sunzi",
  "name": "孫武",
  "nameEn": "Sun Tzu",
  "birth": -544,
  "death": -496,
  "country": "古代中国（呉）",
  "field": "軍事思想家",
  "summary": "春秋時代の軍事思想家。『孫子』の兵法は「戦わずして勝つ」を説き、古代から現代経営まで引用される東洋最高の戦略書。",
  "wikiTitle": "孫武",
  "events": [],
  "quotes": [],
  "places": [],
  "imageUrl": "https://commons.wikimedia.org/wiki/Special:FilePath/%25E5%2590%25B4%25E5%258F%25B8%25E9%25A9%25AC%25E5%25AD%2599%25E6%25AD%25A6.jpg?width=500",
  "books": [],
  "media": [],
  "works": [],
  "routine": {},
  "lifeDigest": "",
  "traits": {},
  "relations": []
}
