{
  "id": "trollope",
  "name": "アンソニー・トロロープ",
  "nameEn": "Anthony Trollope",
  "birth": 1815,
  "death": 1882,
  "birthMonth": 4,
  "birthDay": 24,
  "deathMonth": 12,
  "deathDay": 6,
  "country": "イギリス",
  "field": "小説家",
  "summary": "ヴィクトリア朝イギリスの小説家。朝5時半から毎日3時間決まった量（250語×40ページ）を書き続け、47本の長編を残した。郵便局員として働きながら創作し、イギリスの赤いポストを発案した人物でもある。",
  "events": [
    {
      "year": 1815,
      "age": 0,
      "title": "ロンドンの零落した貴族の家に誕生",
      "detail": "父は法廷弁護士だが破産、母は小説家。少年時代は貧困と孤独の中で過ごした。",
      "tags": [
        "poverty",
        "loss"
      ]
    },
    {
      "year": 1834,
      "age": 19,
      "title": "郵便局に就職",
      "detail": "母のコネで入局。後に33年間勤めることになる定職。",
      "tags": [
        "restart",
        "stability"
      ]
    },
    {
      "year": 1841,
      "age": 26,
      "title": "アイルランドへ転勤、そこで人生が一変",
      "detail": "『アイルランドで、私ははじめて生きはじめた』。馬に乗り、狩りに行き、妻と出会った。",
      "tags": [
        "turning_encounter",
        "gratitude"
      ]
    },
    {
      "year": 1847,
      "age": 32,
      "title": "最初の小説『マクダーモット一家』発表",
      "detail": "ほぼ無視される。それでも毎朝の執筆は続けた。",
      "tags": [
        "first_work",
        "perseverance"
      ]
    },
    {
      "year": 1852,
      "age": 37,
      "title": "イギリスのシンボル『赤いポスト』を提案",
      "detail": "ジャージー島で実験的に設置。以後、英国中の街角に。",
      "tags": [
        "innovation",
        "daily_service"
      ]
    },
    {
      "year": 1855,
      "age": 40,
      "title": "『執事長』で注目される",
      "detail": "バーチェスター物語シリーズの第一作。田舎町の聖職者の世界を描いた。",
      "tags": [
        "breakthrough"
      ]
    },
    {
      "year": 1857,
      "age": 42,
      "title": "『バーチェスターの塔』大ヒット",
      "detail": "ディケンズに並ぶ人気作家の仲間入りを果たした。",
      "tags": [
        "success"
      ]
    },
    {
      "year": 1867,
      "age": 52,
      "title": "郵便局を辞め、文筆に専念",
      "detail": "33年間の勤務。朝の執筆は習慣として残し、亡くなるまで続けた。",
      "tags": [
        "turning_restart"
      ]
    },
    {
      "year": 1875,
      "age": 60,
      "title": "『いま我らが生きる世』発表",
      "detail": "当時のイギリス社会の拝金主義を描いた風刺小説の傑作。",
      "tags": [
        "criticism"
      ]
    },
    {
      "year": 1882,
      "age": 67,
      "title": "脳卒中で倒れ、12月に死去",
      "detail": "ロンドンで執筆中に発作を起こした。47作の小説、短編・旅行記・自伝を残した。",
      "tags": [
        "ending"
      ]
    }
  ],
  "quotes": [
    {
      "text": "すべての人間に必要なのは、ある程度の退屈である。それがなければ、いかなる幸福も成り立たない。",
      "source": "自伝"
    },
    {
      "text": "小説家の仕事は、毎日決まった量を書くことである。インスピレーションを待ってはならない。",
      "source": "自伝"
    },
    {
      "text": "成功の秘訣は、始めた仕事を決して途中で投げ出さないことだ。",
      "source": "書簡"
    }
  ],
  "works": [
    {
      "title": "バーチェスター物語シリーズ（全6作）",
      "year": 1855,
      "type": "小説",
      "description": "架空のバーチェスターを舞台にした田舎町の群像劇。『執事長』『バーチェスターの塔』他。"
    },
    {
      "title": "いま我らが生きる世",
      "year": 1875,
      "type": "小説",
      "description": "ヴィクトリア朝後期の金融資本主義を風刺した長編。"
    },
    {
      "title": "自伝",
      "year": 1883,
      "type": "自伝",
      "description": "死後出版。『毎朝5時半に起きて3時間書く』という執筆ルーティンが赤裸々に語られ、当時は『夢のない作家』と批判された。"
    }
  ],
  "routine": [
    {
      "start": 0,
      "end": 5,
      "activity": "睡眠",
      "cat": "sleep"
    },
    {
      "start": 5,
      "end": 5,
      "activity": "起床（5時半）",
      "cat": "meal"
    },
    {
      "start": 5,
      "end": 8,
      "activity": "執筆（250語/15分のペースで3時間）",
      "cat": "work"
    },
    {
      "start": 8,
      "end": 9,
      "activity": "朝食",
      "cat": "meal"
    },
    {
      "start": 9,
      "end": 17,
      "activity": "郵便局の仕事",
      "cat": "work"
    },
    {
      "start": 17,
      "end": 19,
      "activity": "乗馬・狩り・散歩",
      "cat": "exercise"
    },
    {
      "start": 19,
      "end": 20,
      "activity": "夕食",
      "cat": "meal"
    },
    {
      "start": 20,
      "end": 23,
      "activity": "読書・クラブでの社交",
      "cat": "leisure"
    },
    {
      "start": 23,
      "end": 24,
      "activity": "就寝",
      "cat": "sleep"
    }
  ],
  "lifeDigest": "貧困と孤独の少年時代を過ごした後、郵便局員として33年勤めながら、毎朝5時半から3時間の執筆を続けて47本の長編を残した。インスピレーションを待たず、職人のように文学を生産したことで当時は低く見られたが、20世紀以降再評価され、ヴィクトリア朝を代表する小説家とされる。",
  "traits": {
    "personality": "規律正しく、職人気質。派手を嫌い、日々の積み重ねで成果を出すタイプ。イギリスの「常識」を体現した人物。",
    "foods": [
      "紅茶",
      "マトン料理",
      "ビール"
    ],
    "hobbies": [
      "狩り",
      "乗馬",
      "ホイストゲーム",
      "クラブでの社交",
      "旅行記を書く"
    ],
    "likes": [
      "規則正しい生活",
      "アイルランド",
      "郵便の仕事",
      "ホイスト"
    ],
    "dislikes": [
      "怠惰",
      "インスピレーション頼みの作家",
      "貴族階級の偽善"
    ]
  },
  "relations": [
    {
      "name": "ウィリアム・サッカレー",
      "relation": "盟友・先輩作家",
      "note": "『コーンヒル・マガジン』の編集で連載を組んだ。トロロープが最も敬愛した同時代作家。"
    },
    {
      "name": "チャールズ・ディケンズ",
      "relation": "同時代のライバル",
      "note": "ヴィクトリア朝最大のライバル。トロロープは自伝でディケンズを『感傷的すぎる』と批判した。"
    },
    {
      "name": "ジョージ・エリオット",
      "relation": "尊敬する同時代人"
    },
    {
      "name": "ナサニエル・ホーソーン",
      "relation": "讃えたアメリカの作家",
      "note": "ホーソーンはトロロープの小説を『一片のイングランドを切り取ってガラス瓶に詰めたようだ』と讃えた。"
    },
    {
      "name": "ロバート・トロロープ",
      "relation": "父・破産した法廷弁護士"
    },
    {
      "name": "フランシス・トロロープ",
      "relation": "母・小説家",
      "note": "52歳から執筆を始めて家計を支えた、トロロープの執筆習慣の原点。"
    },
    {
      "name": "ローズ・ヘセルタイン",
      "relation": "妻",
      "years": "1844-1882",
      "note": "アイルランドで出会い、終生連れ添った。"
    },
    {
      "name": "ケイト・フィールド",
      "relation": "精神的な恋の相手",
      "note": "米国のジャーナリスト。友情と恋の間にあった関係。"
    }
  ],
  "imageUrl": "assets/portraits/trollope.webp",
  "wikiTitle": "アンソニー・トロロープ",
  "imageCredit": {
    "artist": "Julia Margaret Cameron",
    "license": "Public domain",
    "sourceUrl": "https://commons.wikimedia.org/wiki/File:Anthony_Trollope_c1870.jpg"
  },
  "imageUrlSource": "https://commons.wikimedia.org/wiki/Special:FilePath/Picture_of_Anthony_Trollope.jpg?width=500"
}
