{
  "id": "zhang_yimou",
  "name": "張芸謀",
  "nameEn": "Zhang Yimou",
  "birth": 1950,
  "death": null,
  "country": "中国",
  "field": "映画監督",
  "summary": "陝西省西安出身、文化大革命で 10 年農村下放を経験。北京電影学院 1 期生として 30 歳でようやく入学、卒業後カメラマンから監督に転身。『紅いコーリャン』『初恋のきた道』『LOVERS』で世界三大映画祭の常連、北京五輪・パラ五輪開閉会式総監督。",
  "wikiTitle": "張芸謀",
  "events": [
    {
      "year": 1950,
      "age": 0,
      "title": "陝西省西安で生まれる",
      "detail": "父は国民党軍医、文化大革命で家族は迫害された。",
      "tags": [
        "loss"
      ]
    },
    {
      "year": 1968,
      "age": 18,
      "title": "文化大革命で 10 年農村下放",
      "detail": "陝西省の農村で労働、後に紡績工場へ。",
      "tags": [
        "isolation"
      ]
    },
    {
      "year": 1978,
      "age": 28,
      "title": "北京電影学院 1 期生に — 規定年齢を超えての特例入学",
      "detail": "鄧小平の書簡で例外入学、撮影学科。",
      "tags": [
        "restart",
        "breakthrough"
      ]
    },
    {
      "year": 1987,
      "age": 37,
      "title": "監督デビュー作『紅いコーリャン』ベルリン金熊賞",
      "detail": "中国映画初のベルリン最高賞、コン・リーをスターに。",
      "tags": [
        "breakthrough",
        "approval"
      ]
    },
    {
      "year": 1990,
      "age": 40,
      "title": "『菊豆』『紅夢』連続でカンヌ・ヴェネチア",
      "detail": "世界三大映画祭の常連へ。",
      "tags": [
        "approval"
      ]
    },
    {
      "year": 2008,
      "age": 58,
      "title": "北京五輪開閉会式総監督",
      "detail": "史上最大規模の演出を成功。",
      "tags": [
        "approval",
        "breakthrough"
      ]
    },
    {
      "year": 2022,
      "age": 72,
      "title": "北京冬季五輪・パラ五輪開閉会式総監督",
      "detail": "夏冬両五輪の開閉式を演出した史上唯一の監督。",
      "tags": [
        "approval"
      ]
    }
  ],
  "quotes": [
    {
      "text": "映画は時代を映し、時代を変える。",
      "source": "インタビュー"
    },
    {
      "text": "色彩は中国映画の言語である。",
      "source": "演出論"
    },
    {
      "text": "農村で過ごした 10 年が、私の最大の財産である。",
      "source": "自伝"
    }
  ],
  "places": [],
  "imageUrl": "assets/portraits/zhang_yimou.webp",
  "books": [],
  "media": [],
  "works": [],
  "lifeDigest": "中国の映画監督。文化大革命で 10 年農村下放後、28 歳で北京電影学院に特例入学、世界三大映画祭の常連監督に。北京夏冬五輪両方の開閉会式総監督を務めた史上唯一の人物。中国映画の世界的代表者。",
  "traits": {},
  "relations": [],
  "innerConflicts": [],
  "turningPoints": [],
  "unknownStories": [],
  "imageUrlSource": "https://commons.wikimedia.org/wiki/Special:FilePath/Zhang_Yimou_from_%22Full_River_Red%22_at_Red_Carpet_of_the_Tokyo_International_Film_Festival_2023_%2853347207442%29.jpg?width=500"
}
